bdat/__init__.py
bdat/__main__.py
bdat/bdat.py
bdat/py.typed
bdat/server.py
bdat/version
bdat/database/__init__.py
bdat/database/py.typed
bdat/database/database/__init__.py
bdat/database/database/collection.py
bdat/database/database/database.py
bdat/database/exceptions/__init__.py
bdat/database/exceptions/database_conflict_exception.py
bdat/database/exceptions/missing_attribute_exception.py
bdat/database/exceptions/unexpected_value_exception.py
bdat/database/kadi/__init__.py
bdat/database/kadi/collection.py
bdat/database/kadi/database.py
bdat/database/storage/__init__.py
bdat/database/storage/entity.py
bdat/database/storage/no_resource_id_exception.py
bdat/database/storage/resource_id.py
bdat/database/storage/resource_param.py
bdat/database/storage/storage.py
bdat/database/util/__init__.py
bdat/database/util/custom_json_encoder.py
bdat/dataimport/__init__.py
bdat/dataimport/import_rules.py
bdat/dataimport/normalize.py
bdat/entities/__init__.py
bdat/entities/data_processing.py
bdat/entities/types.py
bdat/entities/aging/__init__.py
bdat/entities/aging/aging_conditions.py
bdat/entities/aging/aging_data.py
bdat/entities/aging/cell_life.py
bdat/entities/aging/testmatrix.py
bdat/entities/cadi_templates/__init__.py
bdat/entities/cadi_templates/activity.py
bdat/entities/cadi_templates/activityset.py
bdat/entities/cadi_templates/battery.py
bdat/entities/cadi_templates/batteryspecies.py
bdat/entities/cadi_templates/cyclercircuit.py
bdat/entities/cadi_templates/cycling.py
bdat/entities/cadi_templates/device.py
bdat/entities/cadi_templates/devicetype.py
bdat/entities/cadi_templates/entity.py
bdat/entities/cadi_templates/environment.py
bdat/entities/cadi_templates/environmentmeasurement.py
bdat/entities/cadi_templates/environmentsection.py
bdat/entities/cadi_templates/environmentsensor.py
bdat/entities/cadi_templates/geometry.py
bdat/entities/cadi_templates/impedance.py
bdat/entities/cadi_templates/impedancemeasurement.py
bdat/entities/cadi_templates/institution.py
bdat-0.23.2.dist-info/licenses/LICENSE
bdat-0.23.2.dist-info/METADATA
bdat-0.23.2.dist-info/WHEEL
bdat-0.23.2.dist-info/entry_points.txt
bdat-0.23.2.dist-info/top_level.txt
bdat-0.23.2.dist-info/RECORD
